{
  "imo": "9782209",
  "navio": "UNITY SAKURA",
  "gerado_em": "2026-04-17T20:04:10.133Z",
  "estado_atual": {
    "porto": "Itaguaí",
    "em_fundeio": false,
    "local": "-",
    "ultimo_tipo_evento": "SAÍDA",
    "ultima_movimentacao": "2026-04-12T11:00:00.000Z"
  },
  "metricas": {
    "manobras_30d": 2,
    "manobras_180d": 2,
    "manobras_365d": 2,
    "entradas_30d": 1,
    "saidas_30d": 1,
    "mudancas_30d": 0,
    "entradas_365d": 1,
    "saidas_365d": 1,
    "ultima_entrada": "2026-04-07T10:00:00.000Z",
    "ultima_saida": "2026-04-12T11:00:00.000Z",
    "tempo_medio_estadia_horas": 121,
    "tempo_medio_fundeio_horas": null
  },
  "historico_recente": [
    {
      "data": "2026-04-12T11:00:00.000Z",
      "tipo": "SAÍDA",
      "porto": "Itaguaí",
      "de": "TPTE - TERNIUM - THYSSENKRUPP CSA SIDERURGICA DO ATLANTICO",
      "para": "-"
    },
    {
      "data": "2026-04-07T10:00:00.000Z",
      "tipo": "ENTRADA",
      "porto": "Itaguaí",
      "de": "-",
      "para": "TPTE - TERNIUM - THYSSENKRUPP CSA SIDERURGICA DO ATLANTICO"
    }
  ]
}