{
  "1016654": {
    "imo": "1016654",
    "navio": "MSC LEILA",
    "navio_normalizado": "MSC LEILA",
    "porto_atual": "Rio de Janeiro",
    "ultimo_tipo_evento": "ENTRADA",
    "origem_atual": "-",
    "destino_atual": "2C21 - TECON 3 - MRIO",
    "agente_atual": "MSC MEDITERRANEAN SHIPPING BRASIL LTDA",
    "em_fundeio": false,
    "ultima_movimentacao_em": "2026-04-01T21:00:00.000Z",
    "ultimo_hash_evento": "5f012664be25d39534ec870afcc46d073001487283cd5ab48001f37879ecf33f",
    "atualizado_em": "2026-04-01T14:12:06.207Z"
  },
  "1065978": {
    "imo": "1065978",
    "navio": "YA QING ZHI XING",
    "navio_normalizado": "YA QING ZHI XING",
    "porto_atual": "Rio de Janeiro",
    "ultimo_tipo_evento": "ENTRADA",
    "origem_atual": "-",
    "destino_atual": "Fundeio - 2F03 - Feiticeira",
    "agente_atual": "WILSON SONS SHIPPING SERVICES LTDA",
    "em_fundeio": true,
    "ultima_movimentacao_em": "2026-04-01T07:00:00.000Z",
    "ultimo_hash_evento": "dcb73e759e0a8c3f3aac6141460949cd689d6e3bbb9e17759c6675e5516d5fd6",
    "atualizado_em": "2026-04-02T02:01:15.351Z"
  },
  "9231482": {
    "imo": "9231482",
    "navio": "EVRIDIKI G",
    "navio_normalizado": "EVRIDIKI G",
    "porto_atual": "Itaguaí",
    "ultimo_tipo_evento": "ENTRADA",
    "origem_atual": "-",
    "destino_atual": "302 - TECON - SEPETIBA TECON S.A.",
    "agente_atual": "LACHMANN AGÊNCIA MARÍTIMA LTDA",
    "em_fundeio": false,
    "ultima_movimentacao_em": "2026-04-02T05:30:00.000Z",
    "ultimo_hash_evento": "98a740bc343e4a283cf2b583ca97b5516799f2ec11f246c4ad8d430c8930c63e",
    "atualizado_em": "2026-04-02T05:59:35.547Z"
  },
  "9249348": {
    "imo": "9249348",
    "navio": "NORMAND MERMAID",
    "navio_normalizado": "NORMAND MERMAID",
    "porto_atual": "Niterói",
    "ultimo_tipo_evento": "ENTRADA",
    "origem_atual": "-",
    "destino_atual": "Fundeio - 2F6A - LARGO",
    "agente_atual": "INTEREXPRESS SERVIÇOS ADUANEIRO EIRELI",
    "em_fundeio": true,
    "ultima_movimentacao_em": "2026-04-01T10:00:00.000Z",
    "ultimo_hash_evento": "7dfcd793b555b6d0be733a7006fb924eebc70a19aa860b1b84fa964408d9942d",
    "atualizado_em": "2026-04-01T09:30:04.532Z"
  },
  "9253210": {
    "imo": "9253210",
    "navio": "GRANDE BUENOS AIRES",
    "navio_normalizado": "GRANDE BUENOS AIRES",
    "porto_atual": "Rio de Janeiro",
    "ultimo_tipo_evento": "ENTRADA",
    "origem_atual": "-",
    "destino_atual": "2R12 - Terminal - MCAR 1",
    "agente_atual": "LACHMANN AGÊNCIA MARÍTIMA LTDA",
    "em_fundeio": false,
    "ultima_movimentacao_em": "2026-04-02T00:00:00.000Z",
    "ultimo_hash_evento": "ffd2603dd1403376b8cdeb6cf89a840bc31765f6a605c53ac8632ec21597018d",
    "atualizado_em": "2026-04-02T02:01:15.351Z"
  },
  "9288409": {
    "imo": "9288409",
    "navio": "MSC YAMUNA VI",
    "navio_normalizado": "MSC YAMUNA VI",
    "porto_atual": "Rio de Janeiro",
    "ultimo_tipo_evento": "SAÍDA",
    "origem_atual": "2C22 - TECON 2 - MRIO",
    "destino_atual": "-",
    "agente_atual": "MSC MEDITERRANEAN SHIPPING BRASIL LTDA",
    "em_fundeio": false,
    "ultima_movimentacao_em": "2026-04-01T15:30:00.000Z",
    "ultimo_hash_evento": "f6e52b4a6f3640df8a2cf288364e0b8164464c31a3ed92252c00326edfc8e31b",
    "atualizado_em": "2026-04-02T02:01:15.351Z"
  },
  "9309215": {
    "imo": "9309215",
    "navio": "SAN ANDRES IV",
    "navio_normalizado": "SAN ANDRES IV",
    "porto_atual": "Rio de Janeiro",
    "ultimo_tipo_evento": "ENTRADA",
    "origem_atual": "-",
    "destino_atual": "TPS2 - PETROBRAS PS2",
    "agente_atual": "LACHMANN AGÊNCIA MARÍTIMA LTDA",
    "em_fundeio": false,
    "ultima_movimentacao_em": "2026-04-01T17:00:00.000Z",
    "ultimo_hash_evento": "b435a340164237f370fc133c8e62930aeca7fbb5dceda6f25667395fb8f19035",
    "atualizado_em": "2026-04-01T09:30:04.532Z"
  },
  "9329942": {
    "imo": "9329942",
    "navio": "MESTRE DOS MARES (REB)",
    "navio_normalizado": "MESTRE DOS MARES",
    "porto_atual": "Rio de Janeiro",
    "ultimo_tipo_evento": "ENTRADA",
    "origem_atual": "-",
    "destino_atual": "Fundeio - 2F06 - LARGO OESTE",
    "agente_atual": "HOSKEN SERVICOS MARITIMOS LTDA",
    "em_fundeio": true,
    "ultima_movimentacao_em": "2026-04-02T04:00:00.000Z",
    "ultimo_hash_evento": "6b78b54b9b34cf09b3c9f25bb9635724ea15c3b8eda9a0a66179c7ed6137abd3",
    "atualizado_em": "2026-04-02T04:33:33.756Z"
  },
  "9337121": {
    "imo": "9337121",
    "navio": "STAR UNITED",
    "navio_normalizado": "STAR UNITED",
    "porto_atual": "Itaguaí",
    "ultimo_tipo_evento": "SAÍDA",
    "origem_atual": "TPPS - PORTO SUDESTE - PORTO SUDESTE DO BRASIL S.A.",
    "destino_atual": "-",
    "agente_atual": "L.M.A. SHIPPING  CONSULTING",
    "em_fundeio": false,
    "ultima_movimentacao_em": "2026-04-01T08:00:00.000Z",
    "ultimo_hash_evento": "e3bf3861babe0b7a0d4fb8adb0be306795bc0f923cbcc0e4e66e42006cc6e2f0",
    "atualizado_em": "2026-04-01T09:30:04.532Z"
  },
  "9365544": {
    "imo": "9365544",
    "navio": "NAVEGANTES PRIDE",
    "navio_normalizado": "NAVEGANTES PRIDE",
    "porto_atual": "Rio de Janeiro",
    "ultimo_tipo_evento": "MUDANÇA",
    "origem_atual": "TPBR - BRASCO",
    "destino_atual": "Fundeio - 2F6A - LARGO",
    "agente_atual": "BRAM OFFSHORE TRANSPORTES MARÍTIMOS LTDA",
    "em_fundeio": true,
    "ultima_movimentacao_em": "2026-04-01T17:00:00.000Z",
    "ultimo_hash_evento": "5b58c4c1de3b19c22b2700fdee6ecda4ef54737cd996822638bf371333548111",
    "atualizado_em": "2026-04-01T18:09:35.835Z"
  },
  "9385271": {
    "imo": "9385271",
    "navio": "HOS TAURUS (REB)",
    "navio_normalizado": "HOS TAURUS",
    "porto_atual": "Rio de Janeiro",
    "ultimo_tipo_evento": "SAÍDA",
    "origem_atual": "Fundeio - 2F6A - LARGO",
    "destino_atual": "-",
    "agente_atual": "SOLANA AGENCIA MARITIMA LTDA",
    "em_fundeio": false,
    "ultima_movimentacao_em": "2026-04-01T16:30:00.000Z",
    "ultimo_hash_evento": "566f8ff077a0e8596e4af2b80b07baa5704e129f0e1edeea20f75db0e592a6d5",
    "atualizado_em": "2026-04-01T17:02:02.192Z"
  },
  "9385398": {
    "imo": "9385398",
    "navio": "A.H. CAMOGLI (REB)",
    "navio_normalizado": "A.H. CAMOGLI",
    "porto_atual": "Rio de Janeiro",
    "ultimo_tipo_evento": "ENTRADA",
    "origem_atual": "-",
    "destino_atual": "Fundeio - 2F6A - LARGO",
    "agente_atual": "CBO SERVIÇOS MARÍTIMOS LTDA",
    "em_fundeio": true,
    "ultima_movimentacao_em": "2026-04-01T10:00:00.000Z",
    "ultimo_hash_evento": "b4cfa542f03f6f6eee6f9edbcb671a2a91cb36b4c7fb6b678b00d3ecf1a7c31e",
    "atualizado_em": "2026-04-01T09:30:04.532Z"
  },
  "9407392": {
    "imo": "9407392",
    "navio": "HORIZON THEANO",
    "navio_normalizado": "HORIZON THEANO",
    "porto_atual": "Rio de Janeiro",
    "ultimo_tipo_evento": "SAÍDA",
    "origem_atual": "Fundeio - WPT 61 - 2F6A",
    "destino_atual": "-",
    "agente_atual": "LACHMANN AGÊNCIA MARÍTIMA LTDA",
    "em_fundeio": false,
    "ultima_movimentacao_em": "2026-04-01T19:00:00.000Z",
    "ultimo_hash_evento": "2042bf17fdf5fbfb0f839c529a668af810f6627e070e83ab04ad8650e3217109",
    "atualizado_em": "2026-04-01T14:12:06.207Z"
  },
  "9423437": {
    "imo": "9423437",
    "navio": "AKOFS SANTOS",
    "navio_normalizado": "AKOFS SANTOS",
    "porto_atual": "Rio de Janeiro",
    "ultimo_tipo_evento": "ENTRADA",
    "origem_atual": "-",
    "destino_atual": "2TS2 - Terminal Siderúrgico 2",
    "agente_atual": "SMART OFFSHORE AGÊNCIA MARÍTIMA DO BRASIL LTDA",
    "em_fundeio": false,
    "ultima_movimentacao_em": "2026-04-01T10:00:00.000Z",
    "ultimo_hash_evento": "43ceb176deabbb5b7da16fbb87285799e1bc8b5297c6a63fc7fe363a3e181cdc",
    "atualizado_em": "2026-04-01T09:30:04.532Z"
  },
  "9426972": {
    "imo": "9426972",
    "navio": "CBO BIANCA",
    "navio_normalizado": "CBO BIANCA",
    "porto_atual": "Rio de Janeiro",
    "ultimo_tipo_evento": "MUDANÇA",
    "origem_atual": "Fundeio - 2F6A - LARGO",
    "destino_atual": "2N11 - Armazém 13",
    "agente_atual": "CBO SERVIÇOS MARÍTIMOS LTDA",
    "em_fundeio": false,
    "ultima_movimentacao_em": "2026-04-01T07:00:00.000Z",
    "ultimo_hash_evento": "47817f3840ba011b74d52e8215bb9c02555a4ddc1d52a9c28a2bcdf071a2f042",
    "atualizado_em": "2026-04-01T09:30:04.532Z"
  },
  "9429936": {
    "imo": "9429936",
    "navio": "SANCO SPIRIT",
    "navio_normalizado": "SANCO SPIRIT",
    "porto_atual": "Rio de Janeiro",
    "ultimo_tipo_evento": "MUDANÇA",
    "origem_atual": "2N10 - Terminal de Trigo",
    "destino_atual": "Fundeio - 2F6A - LARGO",
    "agente_atual": "SOLANA AGENCIA MARITIMA LTDA",
    "em_fundeio": true,
    "ultima_movimentacao_em": "2026-04-02T01:00:00.000Z",
    "ultimo_hash_evento": "b3ae785b7389a8fcd890a695be22122d93a1310f8a01a63d6b79b72f6c8f31c5",
    "atualizado_em": "2026-04-02T02:01:15.351Z"
  },
  "9440679": {
    "imo": "9440679",
    "navio": "PETREL",
    "navio_normalizado": "PETREL",
    "porto_atual": "Niterói",
    "ultimo_tipo_evento": "ENTRADA",
    "origem_atual": "-",
    "destino_atual": "ESWS - ESTALEIRO",
    "agente_atual": "WILSON SONS OFFSHORE S.A.",
    "em_fundeio": false,
    "ultima_movimentacao_em": "2026-04-01T21:30:00.000Z",
    "ultimo_hash_evento": "d5f79427a3e1a1c50ed1e3d205e44e0dcfb03ceaf40a6b47bbd4013d19b8cbbf",
    "atualizado_em": "2026-04-02T02:01:15.351Z"
  },
  "9440681": {
    "imo": "9440681",
    "navio": "SKUA",
    "navio_normalizado": "SKUA",
    "porto_atual": "Rio de Janeiro",
    "ultimo_tipo_evento": "ENTRADA",
    "origem_atual": "-",
    "destino_atual": "Fundeio - 2F06 - LARGO OESTE",
    "agente_atual": "WILSON SONS OFFSHORE S.A.",
    "em_fundeio": true,
    "ultima_movimentacao_em": "2026-04-01T19:00:00.000Z",
    "ultimo_hash_evento": "66273e3bc4b5727f6e28c90568ee51b5dac9e3476b0f1d0d385a6ddc61d3ad89",
    "atualizado_em": "2026-04-01T20:52:43.233Z"
  },
  "9454151": {
    "imo": "9454151",
    "navio": "CASANOVA",
    "navio_normalizado": "CASANOVA",
    "porto_atual": "Itaguaí",
    "ultimo_tipo_evento": "SAÍDA",
    "origem_atual": "TPPS - PORTO SUDESTE - PORTO SUDESTE DO BRASIL S.A.",
    "destino_atual": "-",
    "agente_atual": "L.M.A. SHIPPING  CONSULTING",
    "em_fundeio": false,
    "ultima_movimentacao_em": "2026-04-01T07:00:00.000Z",
    "ultimo_hash_evento": "4e0d02be95d7a0f5a3f6f59c198c3afe49200387438e7c6a6dac748e7604289e",
    "atualizado_em": "2026-04-01T09:30:04.532Z"
  },
  "9460643": {
    "imo": "9460643",
    "navio": "MINH PROVIDENCE",
    "navio_normalizado": "MINH PROVIDENCE",
    "porto_atual": "Itaguaí",
    "ultimo_tipo_evento": "SAÍDA",
    "origem_atual": "102 - TECAR - CSN MINERAÇÃO S.A.",
    "destino_atual": "-",
    "agente_atual": "ORION RODOS MARITIMA E PORTUARIA LTDA",
    "em_fundeio": false,
    "ultima_movimentacao_em": "2026-04-01T19:00:00.000Z",
    "ultimo_hash_evento": "c89a192575d5f7a909df44ab07d33b30014adb82c354188fede13675a0831a4f",
    "atualizado_em": "2026-04-02T02:01:15.351Z"
  },
  "9500704": {
    "imo": "9500704",
    "navio": "ASL CLASSIC 1",
    "navio_normalizado": "ASL CLASSIC 1",
    "porto_atual": "Itaguaí",
    "ultimo_tipo_evento": "MUDANÇA",
    "origem_atual": "Fundeio - 5FB5 - Área de Fundeio B5",
    "destino_atual": "102 - TECAR - CSN MINERAÇÃO S.A.",
    "agente_atual": "ORION RODOS MARITIMA E PORTUARIA LTDA",
    "em_fundeio": false,
    "ultima_movimentacao_em": "2026-04-01T21:30:00.000Z",
    "ultimo_hash_evento": "cd6e38b1a42ec797d171f31dba52249087fd19ec7e45a91721afa0097cce18d6",
    "atualizado_em": "2026-04-01T14:12:06.207Z"
  },
  "9514212": {
    "imo": "9514212",
    "navio": "CAPE HARMONY",
    "navio_normalizado": "CAPE HARMONY",
    "porto_atual": "Itaguaí",
    "ultimo_tipo_evento": "ENTRADA",
    "origem_atual": "-",
    "destino_atual": "Fundeio - 5FB2 - Área de Fundeio B2",
    "agente_atual": "ORION RODOS MARITIMA E PORTUARIA LTDA",
    "em_fundeio": true,
    "ultima_movimentacao_em": "2026-04-01T11:00:00.000Z",
    "ultimo_hash_evento": "13f112c749054891cc79ea5cba154ef113ff6ad4ed782ff62b4d77b840ff8ec5",
    "atualizado_em": "2026-04-01T09:30:04.532Z"
  },
  "9529700": {
    "imo": "9529700",
    "navio": "POSIDONIA TIGER (REB)",
    "navio_normalizado": "POSIDONIA TIGER",
    "porto_atual": "Rio de Janeiro",
    "ultimo_tipo_evento": "ENTRADA",
    "origem_atual": "-",
    "destino_atual": "Fundeio - 2F06 - LARGO OESTE",
    "agente_atual": "HOSKEN SERVICOS MARITIMOS LTDA",
    "em_fundeio": true,
    "ultima_movimentacao_em": "2026-04-02T00:00:00.000Z",
    "ultimo_hash_evento": "dc1d93660f5ae4287860e69696a44a06facfd4fff8347b7f3c9be64094bdb414",
    "atualizado_em": "2026-04-02T02:01:15.351Z"
  },
  "9530010": {
    "imo": "9530010",
    "navio": "ROBERT ADAMS",
    "navio_normalizado": "ROBERT ADAMS",
    "porto_atual": "Rio de Janeiro",
    "ultimo_tipo_evento": "ENTRADA",
    "origem_atual": "-",
    "destino_atual": "Fundeio - 2F6A - LARGO",
    "agente_atual": "BRAM OFFSHORE TRANSPORTES MARÍTIMOS LTDA",
    "em_fundeio": true,
    "ultima_movimentacao_em": "2026-04-01T16:00:00.000Z",
    "ultimo_hash_evento": "9f2cf9061a43e50e084d04e210d861ab2e262307e007947258215eab3b27595c",
    "atualizado_em": "2026-04-01T09:30:04.532Z"
  },
  "9573440": {
    "imo": "9573440",
    "navio": "NORMAND CARIOCA",
    "navio_normalizado": "NORMAND CARIOCA",
    "porto_atual": "Rio de Janeiro",
    "ultimo_tipo_evento": "ENTRADA",
    "origem_atual": "-",
    "destino_atual": "2TS1 - Terminal Siderúrgico",
    "agente_atual": "SOLSTAD NAVEGAÇÃO MARITIMA LTDA",
    "em_fundeio": false,
    "ultima_movimentacao_em": "2026-04-01T17:00:00.000Z",
    "ultimo_hash_evento": "b2546fd83b40e0f3e0d0d69c53d124a34eb50748fda4fb083882ec25bebdd80b",
    "atualizado_em": "2026-04-01T11:03:35.235Z"
  },
  "9578660": {
    "imo": "9578660",
    "navio": "SEA1 ATLAS",
    "navio_normalizado": "SEA1 ATLAS",
    "porto_atual": "Rio de Janeiro",
    "ultimo_tipo_evento": "ENTRADA",
    "origem_atual": "-",
    "destino_atual": "Fundeio - 2F6A - LARGO",
    "agente_atual": "SOLANA AGENCIA MARITIMA LTDA",
    "em_fundeio": true,
    "ultima_movimentacao_em": "2026-04-02T00:00:00.000Z",
    "ultimo_hash_evento": "729701d9e02712a8e921a1ddfb14391a9e45b4d4144971a19064156941c7b965",
    "atualizado_em": "2026-04-02T02:01:15.351Z"
  },
  "9578672": {
    "imo": "9578672",
    "navio": "SEA1 GIANT",
    "navio_normalizado": "SEA1 GIANT",
    "porto_atual": "Rio de Janeiro",
    "ultimo_tipo_evento": "SAÍDA",
    "origem_atual": "Fundeio - 2F6A - LARGO",
    "destino_atual": "-",
    "agente_atual": "SOLANA AGENCIA MARITIMA LTDA",
    "em_fundeio": false,
    "ultima_movimentacao_em": "2026-04-01T23:00:00.000Z",
    "ultimo_hash_evento": "0dbe292f33de94fceb2e9b7b1a4daaf29a525268f473e1c22088bcbe9b563135",
    "atualizado_em": "2026-04-02T02:01:15.351Z"
  },
  "9591480": {
    "imo": "9591480",
    "navio": "GUO YUAN 32",
    "navio_normalizado": "GUO YUAN 32",
    "porto_atual": "Rio de Janeiro",
    "ultimo_tipo_evento": "SAÍDA",
    "origem_atual": "Fundeio - 2F01 - Visita",
    "destino_atual": "-",
    "agente_atual": "CP SHIPPING",
    "em_fundeio": false,
    "ultima_movimentacao_em": "2026-04-01T10:30:00.000Z",
    "ultimo_hash_evento": "b93fc4da789664cb77f2339acfa90905f43c03c144625eaa09219d3f559672b7",
    "atualizado_em": "2026-04-01T09:30:04.532Z"
  },
  "9596820": {
    "imo": "9596820",
    "navio": "OSCAR NIEMEYER",
    "navio_normalizado": "OSCAR NIEMEYER",
    "porto_atual": "Rio de Janeiro",
    "ultimo_tipo_evento": "MUDANÇA",
    "origem_atual": "Fundeio - WPT 81 - 2F08",
    "destino_atual": "TPIC - ILHA COMPRIDA",
    "agente_atual": "LACHMANN AGÊNCIA MARÍTIMA LTDA",
    "em_fundeio": false,
    "ultima_movimentacao_em": "2026-04-01T12:00:00.000Z",
    "ultimo_hash_evento": "a1855219aadf67884fc8f4c477dd54af0ee422247115a0d9d9657209e76e1c1a",
    "atualizado_em": "2026-04-01T09:30:04.532Z"
  },
  "9619438": {
    "imo": "9619438",
    "navio": "MSC ALBANY",
    "navio_normalizado": "MSC ALBANY",
    "porto_atual": "Rio de Janeiro",
    "ultimo_tipo_evento": "SAÍDA",
    "origem_atual": "2C21 - TECON 3 - MRIO",
    "destino_atual": "-",
    "agente_atual": "MSC MEDITERRANEAN SHIPPING BRASIL LTDA",
    "em_fundeio": false,
    "ultima_movimentacao_em": "2026-04-01T09:00:00.000Z",
    "ultimo_hash_evento": "0770ae16b1cea5b33a7d330431fca4f26d52698f0fdda33e252fd348cf5e9fd9",
    "atualizado_em": "2026-04-01T09:30:04.532Z"
  },
  "9627629": {
    "imo": "9627629",
    "navio": "CBO ARPOADOR",
    "navio_normalizado": "CBO ARPOADOR",
    "porto_atual": "Rio de Janeiro",
    "ultimo_tipo_evento": "MUDANÇA",
    "origem_atual": "2TS1 - Terminal Siderúrgico",
    "destino_atual": "Fundeio - 2F6A - LARGO",
    "agente_atual": "CBO SERVIÇOS MARÍTIMOS LTDA",
    "em_fundeio": true,
    "ultima_movimentacao_em": "2026-04-01T14:00:00.000Z",
    "ultimo_hash_evento": "0489c8cf9e6f79c6fc11ac2253e8009c4b56cacf883c0f6126cc8038a0d89ded",
    "atualizado_em": "2026-04-01T14:12:06.207Z"
  },
  "9636022": {
    "imo": "9636022",
    "navio": "SABLE (REB)",
    "navio_normalizado": "SABLE",
    "porto_atual": "Rio de Janeiro",
    "ultimo_tipo_evento": "ENTRADA",
    "origem_atual": "-",
    "destino_atual": "Fundeio - 2F6A - LARGO",
    "agente_atual": "BRAM OFFSHORE TRANSPORTES MARÍTIMOS LTDA",
    "em_fundeio": true,
    "ultima_movimentacao_em": "2026-04-01T12:00:00.000Z",
    "ultimo_hash_evento": "5b857b85880a076d6b42958832678ff33184f2f69fa518755ddad7f1926cb825",
    "atualizado_em": "2026-04-01T09:30:04.532Z"
  },
  "9636034": {
    "imo": "9636034",
    "navio": "ORYX (REB)",
    "navio_normalizado": "ORYX",
    "porto_atual": "Rio de Janeiro",
    "ultimo_tipo_evento": "SAÍDA",
    "origem_atual": "2P15 - Terminal Petrobrás (Armazém 15)",
    "destino_atual": "-",
    "agente_atual": "BRAM OFFSHORE TRANSPORTES MARÍTIMOS LTDA",
    "em_fundeio": false,
    "ultima_movimentacao_em": "2026-04-02T05:00:00.000Z",
    "ultimo_hash_evento": "be039c0fdc34c90ff9012c83cc644e72d7ab1156c52f1ae698d48be53fe6de12",
    "atualizado_em": "2026-04-02T05:59:35.547Z"
  },
  "9642588": {
    "imo": "9642588",
    "navio": "LARUS",
    "navio_normalizado": "LARUS",
    "porto_atual": "Rio de Janeiro",
    "ultimo_tipo_evento": "ENTRADA",
    "origem_atual": "-",
    "destino_atual": "TPBR - BRASCO",
    "agente_atual": "WILSON SONS OFFSHORE S.A.",
    "em_fundeio": false,
    "ultima_movimentacao_em": "2026-04-01T10:00:00.000Z",
    "ultimo_hash_evento": "3305ead19945ef4f2a4c72f47f115a8dcff029974479d710e71bd544652c24e1",
    "atualizado_em": "2026-04-01T09:30:04.532Z"
  },
  "9644122": {
    "imo": "9644122",
    "navio": "TAGAZ",
    "navio_normalizado": "TAGAZ",
    "porto_atual": "Rio de Janeiro",
    "ultimo_tipo_evento": "SAÍDA",
    "origem_atual": "Fundeio - 2F6A - LARGO",
    "destino_atual": "-",
    "agente_atual": "ROCHAMAR AGÊNCIA MARÍTIMA S.A.",
    "em_fundeio": false,
    "ultima_movimentacao_em": "2026-04-02T05:00:00.000Z",
    "ultimo_hash_evento": "43ac62ef0f898c25256560a09475d7ce333439558fb04ce310fee51e5a353d16",
    "atualizado_em": "2026-04-02T05:59:35.547Z"
  },
  "9644160": {
    "imo": "9644160",
    "navio": "BRAM BELEM",
    "navio_normalizado": "BRAM BELEM",
    "porto_atual": "Rio de Janeiro",
    "ultimo_tipo_evento": "MUDANÇA",
    "origem_atual": "Fundeio - 2F6A - LARGO",
    "destino_atual": "2TS1 - Terminal Siderúrgico",
    "agente_atual": "BRAM OFFSHORE TRANSPORTES MARÍTIMOS LTDA",
    "em_fundeio": false,
    "ultima_movimentacao_em": "2026-04-01T23:00:00.000Z",
    "ultimo_hash_evento": "451d5574289c28fb18cb07f72f2449ce984a75c4f0b561e3c1874cbfeb937405",
    "atualizado_em": "2026-04-02T02:01:15.351Z"
  },
  "9650145": {
    "imo": "9650145",
    "navio": "SOLE",
    "navio_normalizado": "SOLE",
    "porto_atual": "Itaguaí",
    "ultimo_tipo_evento": "SAÍDA",
    "origem_atual": "TPTE - TERNIUM - THYSSENKRUPP CSA SIDERURGICA DO ATLANTICO",
    "destino_atual": "-",
    "agente_atual": "THP SHIPPING AND LOGISTICS LTDA",
    "em_fundeio": false,
    "ultima_movimentacao_em": "2026-04-01T20:00:00.000Z",
    "ultimo_hash_evento": "9ed7ec55194e25db9e4eb89eb8fa10420a95778b3fbabf24c61e71241884bbe4",
    "atualizado_em": "2026-04-01T09:30:04.532Z"
  },
  "9653111": {
    "imo": "9653111",
    "navio": "DELTA CARDINAL (REB)",
    "navio_normalizado": "DELTA CARDINAL",
    "porto_atual": "Rio de Janeiro",
    "ultimo_tipo_evento": "ENTRADA",
    "origem_atual": "-",
    "destino_atual": "Fundeio - 2F6A - LARGO",
    "agente_atual": "CBO SERVIÇOS MARÍTIMOS LTDA",
    "em_fundeio": true,
    "ultima_movimentacao_em": "2026-04-01T12:00:00.000Z",
    "ultimo_hash_evento": "11f98e77bc0ce13dd6e531a6c2a61724e3c27e82144ae8ecbad5da6203938847",
    "atualizado_em": "2026-04-02T02:01:15.351Z"
  },
  "9655494": {
    "imo": "9655494",
    "navio": "ILHA DO MOSQUEIRO (REB)",
    "navio_normalizado": "ILHA DO MOSQUEIRO",
    "porto_atual": "Rio de Janeiro",
    "ultimo_tipo_evento": "SAÍDA",
    "origem_atual": "Fundeio - 2F6A - LARGO",
    "destino_atual": "-",
    "agente_atual": "SOLANA AGENCIA MARITIMA LTDA",
    "em_fundeio": false,
    "ultima_movimentacao_em": "2026-04-01T07:00:00.000Z",
    "ultimo_hash_evento": "89b37fd46e77f39c32b31d5b8a7b380539e7ec9841476b9cf841de7b96b83657",
    "atualizado_em": "2026-04-01T09:30:04.532Z"
  },
  "9668726": {
    "imo": "9668726",
    "navio": "STARNAV PERSEUS",
    "navio_normalizado": "STARNAV PERSEUS",
    "porto_atual": "Rio de Janeiro",
    "ultimo_tipo_evento": "ENTRADA",
    "origem_atual": "-",
    "destino_atual": "ESEN - ESTALEIRO ENAVE / RENAVE",
    "agente_atual": "STARNAV SERVIÇOS MARITIMOS LTDA",
    "em_fundeio": false,
    "ultima_movimentacao_em": "2026-04-02T01:30:00.000Z",
    "ultimo_hash_evento": "fb4c7a2b9fb4a7aeac03b5bae8730bc65078e1b00a582b875736b14777e2d4a9",
    "atualizado_em": "2026-04-02T02:01:15.351Z"
  },
  "9678147": {
    "imo": "9678147",
    "navio": "BRAVANTE II",
    "navio_normalizado": "BRAVANTE II",
    "porto_atual": "Rio de Janeiro",
    "ultimo_tipo_evento": "ENTRADA",
    "origem_atual": "-",
    "destino_atual": "Fundeio - 2F06 - LARGO OESTE",
    "agente_atual": "HOSKEN SERVICOS MARITIMOS LTDA",
    "em_fundeio": true,
    "ultima_movimentacao_em": "2026-04-01T16:30:00.000Z",
    "ultimo_hash_evento": "09921b1d9ea2841bc10f3f7855bfc743885ff3e50a28369b89f4684b0a73f46d",
    "atualizado_em": "2026-04-01T17:02:02.192Z"
  },
  "9687356": {
    "imo": "9687356",
    "navio": "NORMAND NAVIGATOR",
    "navio_normalizado": "NORMAND NAVIGATOR",
    "porto_atual": "Rio de Janeiro",
    "ultimo_tipo_evento": "MUDANÇA",
    "origem_atual": "2TS1 - Terminal Siderúrgico",
    "destino_atual": "Fundeio - 2F6A - LARGO",
    "agente_atual": "SOLSTAD SHIPPING LTDA.",
    "em_fundeio": true,
    "ultima_movimentacao_em": "2026-04-01T18:00:00.000Z",
    "ultimo_hash_evento": "3fbf7bb6d78422f9e9ae5b82b7ae42e8626aa9e0e2e35116795f6a9485f03abf",
    "atualizado_em": "2026-04-02T02:01:15.351Z"
  },
  "9698317": {
    "imo": "9698317",
    "navio": "YANNIS PITTAS",
    "navio_normalizado": "YANNIS PITTAS",
    "porto_atual": "Itaguaí",
    "ultimo_tipo_evento": "ENTRADA",
    "origem_atual": "-",
    "destino_atual": "TPTE - TERNIUM - THYSSENKRUPP CSA SIDERURGICA DO ATLANTICO",
    "agente_atual": "THP SHIPPING AND LOGISTICS LTDA",
    "em_fundeio": false,
    "ultima_movimentacao_em": "2026-04-01T22:30:00.000Z",
    "ultimo_hash_evento": "0381878857d7bdfaa54262742021dec5ca116f2ba1fe7a143cadad4d73141ec8",
    "atualizado_em": "2026-04-01T09:30:04.532Z"
  },
  "9702883": {
    "imo": "9702883",
    "navio": "CBO WISER (REB)",
    "navio_normalizado": "CBO WISER",
    "porto_atual": "Rio de Janeiro",
    "ultimo_tipo_evento": "SAÍDA",
    "origem_atual": "Fundeio - 2F6A - LARGO",
    "destino_atual": "-",
    "agente_atual": "SOLANA AGENCIA MARITIMA LTDA",
    "em_fundeio": false,
    "ultima_movimentacao_em": "2026-04-01T03:00:00.000Z",
    "ultimo_hash_evento": "7cb52989d2df00b3b79cc44f8f63816b29f173dd108f7cd5b9887bacd71a8493",
    "atualizado_em": "2026-04-01T09:30:04.532Z"
  },
  "9706528": {
    "imo": "9706528",
    "navio": "SKANDI BUZIOS",
    "navio_normalizado": "SKANDI BUZIOS",
    "porto_atual": "Rio de Janeiro",
    "ultimo_tipo_evento": "SAÍDA",
    "origem_atual": "TPGE - WELLSTREAM BHGE BARDELA CAXIMBAU",
    "destino_atual": "-",
    "agente_atual": "WILSON SONS SHIPPING SERVICES LTDA",
    "em_fundeio": false,
    "ultima_movimentacao_em": "2026-04-01T11:00:00.000Z",
    "ultimo_hash_evento": "495de2a45cd987bc3cd7c6b2de147b839d4cb9cdaeae8f50a27678c7a970ef38",
    "atualizado_em": "2026-04-01T09:30:04.532Z"
  },
  "9710878": {
    "imo": "9710878",
    "navio": "SEVEN RIO",
    "navio_normalizado": "SEVEN RIO",
    "porto_atual": "Rio de Janeiro",
    "ultimo_tipo_evento": "ENTRADA",
    "origem_atual": "-",
    "destino_atual": "TPGE - WELLSTREAM BHGE BARDELA CAXIMBAU",
    "agente_atual": "WILSON SONS SHIPPING SERVICES LTDA",
    "em_fundeio": false,
    "ultima_movimentacao_em": "2026-04-01T16:00:00.000Z",
    "ultimo_hash_evento": "ef27645fe65701cb80b7ad23fb45b29a89690087968c6fe86f14019cb007c5e7",
    "atualizado_em": "2026-04-01T09:30:04.532Z"
  },
  "9710945": {
    "imo": "9710945",
    "navio": "SEACOR NILE (REB)",
    "navio_normalizado": "SEACOR NILE",
    "porto_atual": "Rio de Janeiro",
    "ultimo_tipo_evento": "ENTRADA",
    "origem_atual": "-",
    "destino_atual": "Fundeio - 2F6A - LARGO",
    "agente_atual": "CMM OFFSHORE BRASIL LTDA",
    "em_fundeio": true,
    "ultima_movimentacao_em": "2026-04-01T14:30:00.000Z",
    "ultimo_hash_evento": "7fe16af42a2cb6b5ab1103210d6f991363632196610f9105e836ad23c05dca83",
    "atualizado_em": "2026-04-02T02:01:15.351Z"
  },
  "9715737": {
    "imo": "9715737",
    "navio": "STARNAV ANDROMEDA",
    "navio_normalizado": "STARNAV ANDROMEDA",
    "porto_atual": "Rio de Janeiro",
    "ultimo_tipo_evento": "SAÍDA",
    "origem_atual": "2TS1 - Terminal Siderúrgico",
    "destino_atual": "-",
    "agente_atual": "STARNAV SERVIÇOS MARITIMOS LTDA",
    "em_fundeio": false,
    "ultima_movimentacao_em": "2026-04-01T18:00:00.000Z",
    "ultimo_hash_evento": "33a4cb64ec59199887da1e90dcc3338d366dc70b37940fd8c0935495074d44e8",
    "atualizado_em": "2026-04-01T18:09:35.835Z"
  },
  "9747314": {
    "imo": "9747314",
    "navio": "CL TAIZHOU",
    "navio_normalizado": "CL TAIZHOU",
    "porto_atual": "Rio de Janeiro",
    "ultimo_tipo_evento": "SAÍDA",
    "origem_atual": "Fundeio - 2F01S - Visita Sul",
    "destino_atual": "-",
    "agente_atual": "ORION RODOS MARITIMA E PORTUARIA LTDA",
    "em_fundeio": false,
    "ultima_movimentacao_em": "2026-04-01T11:00:00.000Z",
    "ultimo_hash_evento": "4f46b4b7a86eaf7bcdc2d5021d70734d5819c0c05dea88afe1d84bb3bcdf13e2",
    "atualizado_em": "2026-04-01T09:30:04.532Z"
  },
  "9759496": {
    "imo": "9759496",
    "navio": "STARNAV VOLANS",
    "navio_normalizado": "STARNAV VOLANS",
    "porto_atual": "Rio de Janeiro",
    "ultimo_tipo_evento": "MUDANÇA",
    "origem_atual": "2P19 - Terminal Petrobrás SC",
    "destino_atual": "Fundeio - 2F6A - LARGO",
    "agente_atual": "STARNAV SERVIÇOS MARITIMOS LTDA",
    "em_fundeio": true,
    "ultima_movimentacao_em": "2026-04-01T07:00:00.000Z",
    "ultimo_hash_evento": "bae5c3a8931c56a4402e6bea80c8fb5f4777914bc4f39350f0c73a21a12613b3",
    "atualizado_em": "2026-04-01T09:30:04.532Z"
  },
  "9762742": {
    "imo": "9762742",
    "navio": "POSIDONIA LEOPARD (REB)",
    "navio_normalizado": "POSIDONIA LEOPARD",
    "porto_atual": "Rio de Janeiro",
    "ultimo_tipo_evento": "MUDANÇA",
    "origem_atual": "2TS1 - Terminal Siderúrgico",
    "destino_atual": "Fundeio - 2F06 - LARGO OESTE",
    "agente_atual": "HOSKEN SERVICOS MARITIMOS LTDA",
    "em_fundeio": true,
    "ultima_movimentacao_em": "2026-04-01T05:00:00.000Z",
    "ultimo_hash_evento": "357f9893ef6ae7f83a16288c25077fcf0a1ad25578c42e9a9d605e78558484b0",
    "atualizado_em": "2026-04-01T09:30:04.532Z"
  },
  "9766621": {
    "imo": "9766621",
    "navio": "CBO ALIANÇA",
    "navio_normalizado": "CBO ALIANCA",
    "porto_atual": "Rio de Janeiro",
    "ultimo_tipo_evento": "MUDANÇA",
    "origem_atual": "Fundeio - 2F6A - LARGO",
    "destino_atual": "2P19 - Terminal Petrobrás SC",
    "agente_atual": "COMPANHIA BRASILEIRA DE OFFSHORE - CBO",
    "em_fundeio": false,
    "ultima_movimentacao_em": "2026-04-01T16:00:00.000Z",
    "ultimo_hash_evento": "bfec2513a0333fe1f86ee61f24dc89330b8d5c68992dc3e4a0ce6d44385fb7ea",
    "atualizado_em": "2026-04-01T14:12:06.207Z"
  },
  "9769221": {
    "imo": "9769221",
    "navio": "ANNA KNUTSEN",
    "navio_normalizado": "ANNA KNUTSEN",
    "porto_atual": "Rio de Janeiro",
    "ultimo_tipo_evento": "SAÍDA",
    "origem_atual": "Fundeio - 2F01 - Visita",
    "destino_atual": "-",
    "agente_atual": "GAC DO BRASIL LTDA.",
    "em_fundeio": false,
    "ultima_movimentacao_em": "2026-04-01T14:00:00.000Z",
    "ultimo_hash_evento": "c489b6ea0463dad07ff2932b1df4457d907e66345f3cb9882e0bdd8f88aab87f",
    "atualizado_em": "2026-04-01T14:12:06.207Z"
  },
  "9788411": {
    "imo": "9788411",
    "navio": "BRAM POWER",
    "navio_normalizado": "BRAM POWER",
    "porto_atual": "Rio de Janeiro",
    "ultimo_tipo_evento": "ENTRADA",
    "origem_atual": "-",
    "destino_atual": "Fundeio - 2F6A - LARGO",
    "agente_atual": "BRAM OFFSHORE TRANSPORTES MARÍTIMOS LTDA",
    "em_fundeio": true,
    "ultima_movimentacao_em": "2026-04-01T09:00:00.000Z",
    "ultimo_hash_evento": "418a95a82e1b5ec5a7de8f273b115b146b4b94f3de7e43ff810c80ded7075adb",
    "atualizado_em": "2026-04-01T09:30:04.532Z"
  },
  "9801196": {
    "imo": "9801196",
    "navio": "MONDIAL COSMOS",
    "navio_normalizado": "MONDIAL COSMOS",
    "porto_atual": "Rio de Janeiro",
    "ultimo_tipo_evento": "ENTRADA",
    "origem_atual": "-",
    "destino_atual": "Fundeio - 2F01S - Visita Sul",
    "agente_atual": "ORION RODOS MARITIMA E PORTUARIA LTDA",
    "em_fundeio": true,
    "ultima_movimentacao_em": "2026-04-01T10:00:00.000Z",
    "ultimo_hash_evento": "0386ce260fa73250995ddf73ececc51fc593d7dd44ec3d4574b0bcc669963b60",
    "atualizado_em": "2026-04-02T02:01:15.351Z"
  },
  "9806512": {
    "imo": "9806512",
    "navio": "STARNAV DELPHINUS",
    "navio_normalizado": "STARNAV DELPHINUS",
    "porto_atual": "Rio de Janeiro",
    "ultimo_tipo_evento": "ENTRADA",
    "origem_atual": "-",
    "destino_atual": "Fundeio - 2F6A - LARGO",
    "agente_atual": "STARNAV SERVIÇOS MARITIMOS LTDA",
    "em_fundeio": true,
    "ultima_movimentacao_em": "2026-04-01T20:30:00.000Z",
    "ultimo_hash_evento": "2419ec076dfd5edbb617c3573da209b2a5c1711195d969939d4e917db0c70a5c",
    "atualizado_em": "2026-04-01T21:49:28.146Z"
  },
  "9814973": {
    "imo": "9814973",
    "navio": "SEALOADER 2",
    "navio_normalizado": "SEALOADER 2",
    "porto_atual": "Rio de Janeiro",
    "ultimo_tipo_evento": "SAÍDA",
    "origem_atual": "Fundeio - 2F6A - LARGO",
    "destino_atual": "-",
    "agente_atual": "LACHMANN AGÊNCIA MARÍTIMA LTDA",
    "em_fundeio": false,
    "ultima_movimentacao_em": "2026-04-01T22:00:00.000Z",
    "ultimo_hash_evento": "4114985de24daf0aec9305aee4b1fa2ac68a25180c73f698f923660f97bb64f1",
    "atualizado_em": "2026-04-01T22:44:55.707Z"
  },
  "9850862": {
    "imo": "9850862",
    "navio": "EVER FAR",
    "navio_normalizado": "EVER FAR",
    "porto_atual": "Rio de Janeiro",
    "ultimo_tipo_evento": "ENTRADA",
    "origem_atual": "-",
    "destino_atual": "2C12 - TECON PROLONG - ICTSI - ICTSI RIO BRASILTERMINAL 1 S.A",
    "agente_atual": "BERGESEN DO BRASIL PARTICIPAÇÕES LTDA",
    "em_fundeio": false,
    "ultima_movimentacao_em": "2026-04-01T16:30:00.000Z",
    "ultimo_hash_evento": "65de40aacb6ed8f0d8e0e638f04a169472d84b527c65a41731ff655c5f043f91",
    "atualizado_em": "2026-04-01T09:30:04.532Z"
  },
  "9851282": {
    "imo": "9851282",
    "navio": "BERGE DACHSTEIN",
    "navio_normalizado": "BERGE DACHSTEIN",
    "porto_atual": "Itaguaí",
    "ultimo_tipo_evento": "ENTRADA",
    "origem_atual": "-",
    "destino_atual": "TPPS - PORTO SUDESTE - PORTO SUDESTE DO BRASIL S.A.",
    "agente_atual": "GEM SHIPPING LTDA",
    "em_fundeio": false,
    "ultima_movimentacao_em": "2026-04-01T11:00:00.000Z",
    "ultimo_hash_evento": "a8509e0d894d8dd1dbca7b4d8e2a90f6b2158bb96d30924b1433918eba63656f",
    "atualizado_em": "2026-04-01T09:30:04.532Z"
  },
  "9938248": {
    "imo": "9938248",
    "navio": "CMA CGM BAHIA",
    "navio_normalizado": "CMA CGM BAHIA",
    "porto_atual": "Rio de Janeiro",
    "ultimo_tipo_evento": "SAÍDA",
    "origem_atual": "2C12 - TECON PROLONG - ICTSI - ICTSI RIO BRASILTERMINAL 1 S.A",
    "destino_atual": "-",
    "agente_atual": "UNIMAR AGENCIAMENTOS MARITIMOS LTDA",
    "em_fundeio": false,
    "ultima_movimentacao_em": "2026-04-01T19:00:00.000Z",
    "ultimo_hash_evento": "eaaab02e47fe6941190f6098332e1ee23eaff9e41505c6e4c759ac80b10df10d",
    "atualizado_em": "2026-04-02T02:01:15.351Z"
  },
  "9945849": {
    "imo": "9945849",
    "navio": "COSCO SHIPPING ARGENTINA",
    "navio_normalizado": "COSCO SHIPPING ARGENTINA",
    "porto_atual": "Rio de Janeiro",
    "ultimo_tipo_evento": "SAÍDA",
    "origem_atual": "2C12 - TECON PROLONG - ICTSI - ICTSI RIO BRASILTERMINAL 1 S.A",
    "destino_atual": "-",
    "agente_atual": "UNIMAR AGENCIAMENTOS MARITIMOS LTDA",
    "em_fundeio": false,
    "ultima_movimentacao_em": "2026-04-01T16:30:00.000Z",
    "ultimo_hash_evento": "6bbd005995bef8bce1e68045f4a52196a6f26c7a5f6a89ce74a7224cfecfbd46",
    "atualizado_em": "2026-04-02T02:01:15.351Z"
  },
  "9946300": {
    "imo": "9946300",
    "navio": "NS PIONEER",
    "navio_normalizado": "NS PIONEER",
    "porto_atual": "Rio de Janeiro",
    "ultimo_tipo_evento": "ENTRADA",
    "origem_atual": "-",
    "destino_atual": "Fundeio - 2F01S - Visita Sul",
    "agente_atual": "ISS MARINE SERVICES LTDA",
    "em_fundeio": true,
    "ultima_movimentacao_em": "2026-04-01T09:00:00.000Z",
    "ultimo_hash_evento": "9c6fcfeb7f8f4848691da2ae35d9b13b2b5bb27a10fc8620a170629143b26387",
    "atualizado_em": "2026-04-01T09:30:04.532Z"
  },
  "9965837": {
    "imo": "9965837",
    "navio": "YM MASCOT",
    "navio_normalizado": "YM MASCOT",
    "porto_atual": "Itaguaí",
    "ultimo_tipo_evento": "SAÍDA",
    "origem_atual": "TPTE - TERNIUM - THYSSENKRUPP CSA SIDERURGICA DO ATLANTICO",
    "destino_atual": "-",
    "agente_atual": "GEM SHIPPING LTDA",
    "em_fundeio": false,
    "ultima_movimentacao_em": "2026-04-02T02:00:00.000Z",
    "ultimo_hash_evento": "dc0a8da813e3ef9e58f56ac00b2666d95590649f6170f6c4689fc93f7d534eea",
    "atualizado_em": "2026-04-02T02:01:15.351Z"
  },
  "9969065": {
    "imo": "9969065",
    "navio": "MAERSK FRANKFURT",
    "navio_normalizado": "MAERSK FRANKFURT",
    "porto_atual": "Rio de Janeiro",
    "ultimo_tipo_evento": "ENTRADA",
    "origem_atual": "-",
    "destino_atual": "2C11 - TECON - ICTSI 1",
    "agente_atual": "LACHMANN AGÊNCIA MARÍTIMA LTDA",
    "em_fundeio": false,
    "ultima_movimentacao_em": "2026-04-02T02:00:00.000Z",
    "ultimo_hash_evento": "4e5e4e5f520d26f34c19112921cba3789f5d4ff9fdfbde15be33b3818b00ca0a",
    "atualizado_em": "2026-04-02T02:01:15.351Z"
  },
  "9976472": {
    "imo": "9976472",
    "navio": "GREEN VITORIA",
    "navio_normalizado": "GREEN VITORIA",
    "porto_atual": "Itaguaí",
    "ultimo_tipo_evento": "SAÍDA",
    "origem_atual": "302 - TECON - SEPETIBA TECON S.A.",
    "destino_atual": "-",
    "agente_atual": "ISS MARINE SERVICES LTDA",
    "em_fundeio": false,
    "ultima_movimentacao_em": "2026-04-02T01:00:00.000Z",
    "ultimo_hash_evento": "d72565d05002533dccfc033d9209c8be2b8bb35024d5d9df261b6bbfdf01a491",
    "atualizado_em": "2026-04-02T02:01:15.351Z"
  },
  "3813877914": {
    "imo": "3813877914",
    "navio": "EQUIP 190",
    "navio_normalizado": "EQUIP 190",
    "porto_atual": "Rio de Janeiro",
    "ultimo_tipo_evento": "MUDANÇA",
    "origem_atual": "2N11 - Armazém 13",
    "destino_atual": "ESCM - ESTALEIRO CAMORIM",
    "agente_atual": "CAMORIM SERVIÇOS MARÍTIMOS LTDA",
    "em_fundeio": false,
    "ultima_movimentacao_em": "2026-04-01T19:30:00.000Z",
    "ultimo_hash_evento": "cf26432c190e7b4758ff7c6f6c0ab8c4a7c4162fdfe51eebd84c4d0d2b5fcb07",
    "atualizado_em": "2026-04-02T02:01:15.351Z"
  },
  "0011466537": {
    "imo": "0011466537",
    "navio": "BONO II",
    "navio_normalizado": "BONO II",
    "porto_atual": "Rio de Janeiro",
    "ultimo_tipo_evento": "MUDANÇA",
    "origem_atual": "Fundeio - 2F6A - LARGO",
    "destino_atual": "Fundeio - 2F6A - LARGO",
    "agente_atual": "SHIPLOG SERVIÇOS DE AGENCIAMENTO MARÍTIMO E LOGÍSTICA LTDA.",
    "em_fundeio": true,
    "ultima_movimentacao_em": "2026-04-01T20:00:00.000Z",
    "ultimo_hash_evento": "7ced6670653cc5dbe2e4682624ade01a1496fee1addaf222160d9d21a1cb75d2",
    "atualizado_em": "2026-04-01T11:03:35.235Z"
  }
}