{
  "periodos": {
    "30d": [
      {
        "posicao": 1,
        "imo": "1019905",
        "navio": "BRAM RIO",
        "porto": "Rio de Janeiro",
        "manobras": 13
      },
      {
        "posicao": 2,
        "imo": "9763760",
        "navio": "BRAM BUCK",
        "porto": "Rio de Janeiro",
        "manobras": 12
      },
      {
        "posicao": 3,
        "imo": "9766621",
        "navio": "CBO ALIANÇA",
        "porto": "Rio de Janeiro",
        "manobras": 12
      },
      {
        "posicao": 4,
        "imo": "9703667",
        "navio": "BRAM HERO",
        "porto": "Rio de Janeiro",
        "manobras": 11
      },
      {
        "posicao": 5,
        "imo": "9715751",
        "navio": "STARNAV PHOENIX",
        "porto": "Rio de Janeiro",
        "manobras": 11
      },
      {
        "posicao": 6,
        "imo": "9752967",
        "navio": "SEACOR DEMERARA (REB)",
        "porto": "Rio de Janeiro",
        "manobras": 11
      },
      {
        "posicao": 7,
        "imo": "9442055",
        "navio": "TALHA-MAR",
        "porto": "Rio de Janeiro",
        "manobras": 10
      },
      {
        "posicao": 8,
        "imo": "9477397",
        "navio": "CBO CAROLINA",
        "porto": "Rio de Janeiro",
        "manobras": 10
      },
      {
        "posicao": 9,
        "imo": "9497139",
        "navio": "SANTOS SUPPLIER",
        "porto": "Rio de Janeiro",
        "manobras": 10
      },
      {
        "posicao": 10,
        "imo": "9578892",
        "navio": "CBO COPACABANA",
        "porto": "Niterói",
        "manobras": 10
      }
    ],
    "180d": [
      {
        "posicao": 1,
        "imo": "1019905",
        "navio": "BRAM RIO",
        "porto": "Rio de Janeiro",
        "manobras": 13
      },
      {
        "posicao": 2,
        "imo": "9763760",
        "navio": "BRAM BUCK",
        "porto": "Rio de Janeiro",
        "manobras": 12
      },
      {
        "posicao": 3,
        "imo": "9766621",
        "navio": "CBO ALIANÇA",
        "porto": "Rio de Janeiro",
        "manobras": 12
      },
      {
        "posicao": 4,
        "imo": "9703667",
        "navio": "BRAM HERO",
        "porto": "Rio de Janeiro",
        "manobras": 11
      },
      {
        "posicao": 5,
        "imo": "9715751",
        "navio": "STARNAV PHOENIX",
        "porto": "Rio de Janeiro",
        "manobras": 11
      },
      {
        "posicao": 6,
        "imo": "9752967",
        "navio": "SEACOR DEMERARA (REB)",
        "porto": "Rio de Janeiro",
        "manobras": 11
      },
      {
        "posicao": 7,
        "imo": "9442055",
        "navio": "TALHA-MAR",
        "porto": "Rio de Janeiro",
        "manobras": 10
      },
      {
        "posicao": 8,
        "imo": "9477397",
        "navio": "CBO CAROLINA",
        "porto": "Rio de Janeiro",
        "manobras": 10
      },
      {
        "posicao": 9,
        "imo": "9497139",
        "navio": "SANTOS SUPPLIER",
        "porto": "Rio de Janeiro",
        "manobras": 10
      },
      {
        "posicao": 10,
        "imo": "9578892",
        "navio": "CBO COPACABANA",
        "porto": "Niterói",
        "manobras": 10
      }
    ],
    "365d": [
      {
        "posicao": 1,
        "imo": "1019905",
        "navio": "BRAM RIO",
        "porto": "Rio de Janeiro",
        "manobras": 13
      },
      {
        "posicao": 2,
        "imo": "9763760",
        "navio": "BRAM BUCK",
        "porto": "Rio de Janeiro",
        "manobras": 12
      },
      {
        "posicao": 3,
        "imo": "9766621",
        "navio": "CBO ALIANÇA",
        "porto": "Rio de Janeiro",
        "manobras": 12
      },
      {
        "posicao": 4,
        "imo": "9703667",
        "navio": "BRAM HERO",
        "porto": "Rio de Janeiro",
        "manobras": 11
      },
      {
        "posicao": 5,
        "imo": "9715751",
        "navio": "STARNAV PHOENIX",
        "porto": "Rio de Janeiro",
        "manobras": 11
      },
      {
        "posicao": 6,
        "imo": "9752967",
        "navio": "SEACOR DEMERARA (REB)",
        "porto": "Rio de Janeiro",
        "manobras": 11
      },
      {
        "posicao": 7,
        "imo": "9442055",
        "navio": "TALHA-MAR",
        "porto": "Rio de Janeiro",
        "manobras": 10
      },
      {
        "posicao": 8,
        "imo": "9477397",
        "navio": "CBO CAROLINA",
        "porto": "Rio de Janeiro",
        "manobras": 10
      },
      {
        "posicao": 9,
        "imo": "9497139",
        "navio": "SANTOS SUPPLIER",
        "porto": "Rio de Janeiro",
        "manobras": 10
      },
      {
        "posicao": 10,
        "imo": "9578892",
        "navio": "CBO COPACABANA",
        "porto": "Niterói",
        "manobras": 10
      }
    ]
  },
  "atualizado_em": "2026-04-21T22:57:31.819Z"
}